spotify/__init__.py
spotify/spotify.py
spotify_me-0.0.1.dist-info/LICENSE
spotify_me-0.0.1.dist-info/METADATA
spotify_me-0.0.1.dist-info/WHEEL
spotify_me-0.0.1.dist-info/top_level.txt
spotify_me-0.0.1.dist-info/RECORD
