Metadata-Version: 2.1
Name: spotify-me
Version: 0.0.1
Summary: A SpotifyAPI Client that is straightforward and works easily
Home-page: https://github.com/erdos2n/spotifyAPI
Author: Rafael Carrasco
Author-email: rafacarrasco07@gmail.com
License: GPL
Platform: UNKNOWN
Classifier: Programming Language :: Python :: 3
Classifier: Operating System :: OS Independent
Requires-Python: >=3.6
